LICENSE
README.md
setup.py
FEADRE_AI/FGLOBAL_VAR.py
FEADRE_AI/GLOBAL_LOG.py
FEADRE_AI/__init__.py
FEADRE_AI/f_general.py
FEADRE_AI.egg-info/PKG-INFO
FEADRE_AI.egg-info/SOURCES.txt
FEADRE_AI.egg-info/dependency_links.txt
FEADRE_AI.egg-info/top_level.txt
FEADRE_AI/ai/CONFIG_BASE.py
FEADRE_AI/ai/__init__.py
FEADRE_AI/ai/calc/__init__.py
FEADRE_AI/ai/calc/f_calc_adv.py
FEADRE_AI/ai/calc/f_calc_dim.py
FEADRE_AI/ai/calc/flops_counter.py
FEADRE_AI/ai/calc/t_torch.py
FEADRE_AI/ai/calc/x_nms.py
FEADRE_AI/ai/datas/__init__.py
FEADRE_AI/ai/datas/data_factory.py
FEADRE_AI/ai/datas/dataset_coco.py
FEADRE_AI/ai/datas/z_dataloader.py
FEADRE_AI/ai/datas/coco/__init__.py
FEADRE_AI/ai/datas/coco/coco_api.py
FEADRE_AI/ai/datas/coco/fcocoeval.py
FEADRE_AI/ai/datas/dta_heighten/__init__.py
FEADRE_AI/ai/datas/dta_heighten/data_color_handler.py
FEADRE_AI/ai/datas/dta_heighten/f_data_heighten4target.py
FEADRE_AI/ai/datas/dta_heighten/f_data_heighten_matrix.py
FEADRE_AI/ai/datas/dta_heighten/fmosaic.py
FEADRE_AI/ai/fits/__init__.py
FEADRE_AI/ai/fits/f_fit_tools.py
FEADRE_AI/ai/fits/f_predictfun.py
FEADRE_AI/ai/fits/fit_handler.py
FEADRE_AI/ai/fits/fweight.py
FEADRE_AI/ai/fits/hadler_weight.py
FEADRE_AI/ai/fits/olf/__init__.py
FEADRE_AI/ai/fits/olf/floss.py
FEADRE_AI/ai/fits/olf/lr_scheduler.py
FEADRE_AI/ai/fmodels/__init__.py
FEADRE_AI/ai/fmodels/f_fun_activation.py
FEADRE_AI/ai/fmodels/f_layer_get.py
FEADRE_AI/ai/fmodels/model_feature.py
FEADRE_AI/ai/fmodels/model_fpn.py
FEADRE_AI/ai/fmodels/model_look.py
FEADRE_AI/ai/fmodels/model_modules.py
FEADRE_AI/ai/fmodels/model_subassembly.py
FEADRE_AI/ai/fmodels/x_funs_model.py
FEADRE_AI/ai/fmodels/backbone/__init__.py
FEADRE_AI/ai/fmodels/backbone/cspdarknet.py
FEADRE_AI/ai/fmodels/backbone/darknet.py
FEADRE_AI/ai/fmodels/backbone/net_blocks.py
FEADRE_AI/ai/fmodels/tools/__init__.py
FEADRE_AI/ai/fmodels/tools/ema.py
FEADRE_AI/ai/fmodels/tools/t_model_fun.py
FEADRE_AI/ai/gpu/__init__.py
FEADRE_AI/ai/gpu/t_gpu.py
FEADRE_AI/ai/gpu/webapi/__init__.py
FEADRE_AI/ai/gpu/webapi/translate.py
FEADRE_AI/ai/match_loss/__init__.py
FEADRE_AI/ai/match_loss/fmatch.py
