Metadata-Version: 2.1
Name: FEADRE-AI
Version: 1.0.7
Summary: My short description for my project.
Home-page: https://gitee.com/feadre/feadre-ai.git
Author: FEADRE
Author-email: 318740003@qq.com
License: UNKNOWN
Platform: UNKNOWN
Classifier: Programming Language :: Python :: 3.7
Classifier: License :: OSI Approved :: MIT License
Classifier: Operating System :: OS Independent
Requires-Python: >=3.7
License-File: LICENSE
